ottrlib/Ottr.py
ottrlib/__init__.py
ottrlib/__main__.py
ottrlib/grammar/Turtle.interp
ottrlib/grammar/Turtle.tokens
ottrlib/grammar/TurtleLexer.interp
ottrlib/grammar/TurtleLexer.py
ottrlib/grammar/TurtleLexer.tokens
ottrlib/grammar/TurtleParser.py
ottrlib/grammar/TurtleVisitor.py
ottrlib/grammar/__init__.py
ottrlib/grammar/stOTTR.interp
ottrlib/grammar/stOTTR.tokens
ottrlib/grammar/stOTTRLexer.interp
ottrlib/grammar/stOTTRLexer.py
ottrlib/grammar/stOTTRLexer.tokens
ottrlib/grammar/stOTTRParser.py
ottrlib/grammar/stOTTRVisitor.py
ottrlib/model.py
ottrlib/ottr_demo.py
ottrlib/stOTTRVisitor.py
ottrlib/validators.py
ottrlib-0.1.1.dist-info/LICENSE
ottrlib-0.1.1.dist-info/METADATA
ottrlib-0.1.1.dist-info/WHEEL
ottrlib-0.1.1.dist-info/RECORD
