Metadata-Version: 2.1
Name: ottrlib
Version: 0.1.1
Summary: An implementation of Resonable Ontology Template (OTTR) for Python.
License: MIT
Keywords: feed,reader,tutorial
Author: Michał Poręba
Author-email: michalporeba@gmail.com
Requires-Python: >=3.11,<4.0
Classifier: Development Status :: 3 - Alpha
Classifier: License :: OSI Approved :: MIT License
Classifier: Programming Language :: Python
Classifier: Programming Language :: Python :: 3
Classifier: Programming Language :: Python :: 3.11
Requires-Dist: antlr4-python3-runtime (==4.13)
Requires-Dist: diogi (>=0.0.9,<0.0.10)
